atomic_operator/__init__.py
atomic_operator/__main__.py
atomic_operator/atomic/__init__.py
atomic_operator/atomic/atomic.py
atomic_operator/atomic/atomictest.py
atomic_operator/atomic/loader.py
atomic_operator/atomic_operator.py
atomic_operator/base.py
atomic_operator/configparser.py
atomic_operator/data/logging.yml
atomic_operator/execution/__init__.py
atomic_operator/execution/awsrunner.py
atomic_operator/execution/copier.py
atomic_operator/execution/localrunner.py
atomic_operator/execution/remoterunner.py
atomic_operator/execution/runner.py
atomic_operator/execution/statemachine.py
atomic_operator/models.py
atomic_operator/utils/__init__.py
atomic_operator/utils/exceptions.py
atomic_operator/utils/logger.py
atomic_operator-0.9.0.dist-info/LICENSE.md
atomic_operator-0.9.0.dist-info/WHEEL
atomic_operator-0.9.0.dist-info/METADATA
atomic_operator-0.9.0.dist-info/entry_points.txt
atomic_operator-0.9.0.dist-info/RECORD
