Metadata-Version: 2.1
Name: atomic-operator
Version: 0.9.0
Summary: A python package to execute security tests on remote and local hosts
Home-page: https://atomic-operator.com
License: MIT
Author: MSAdministrator
Author-email: MSAdministrator@users.noreply.github.com
Maintainer: MSAdministrator
Maintainer-email: MSAdministrator@users.noreply.github.com
Requires-Python: >=3.8,<4.0
Classifier: License :: OSI Approved :: MIT License
Classifier: Programming Language :: Python :: 3
Classifier: Programming Language :: Python :: 3.8
Classifier: Programming Language :: Python :: 3.9
Classifier: Programming Language :: Python :: 3.10
Classifier: Programming Language :: Python :: 3.11
Requires-Dist: atomic-operator-runner (>=0.2.1,<0.3.0)
Requires-Dist: fire (>=0.5.0,<0.6.0)
Requires-Dist: pick (>=2.2.0,<3.0.0)
Requires-Dist: rich (>=13.3.1,<14.0.0)
Project-URL: Documentation, https://atomic-operator.com
Project-URL: Repository, https://github.com/swimlane/atomic-operator
